{
    "@id": "https:\/\/404mike.github.io\/testiiif\/canvas\/389627.json",
    "@context": "http:\/\/iiif.io\/api\/presentation\/2\/context.json",
    "@type": "sc:Canvas",
    "label": "Image for node 389627",
    "width": 710,
    "height": 1115,
    "images": [
        {
            "@type": "oa:Annotation",
            "@id": "https:\/\/404mike.github.io\/testiiif\/6827\/annotation\/389627.json",
            "motivation": "sc:painting",
            "on": "https:\/\/404mike.github.io\/testiiif\/canvas\/389627.json",
            "resource": {
                "@type": "dctypes:Image",
                "@id": "https:\/\/www.peoplescollection.wales\/sites\/default\/files\/images\/2014\/September\/Snook0001.jpg",
                "width": 710,
                "height": 1115,
                "format": "image\/jpeg"
            }
        }
    ]
}